bb_wrapper/__init__.py
bb_wrapper/constants.py
bb_wrapper/models/__init__.py
bb_wrapper/models/barcode.py
bb_wrapper/models/boleto.py
bb_wrapper/models/pagamentos.py
bb_wrapper/models/perfis.py
bb_wrapper/models/pix_cob.py
bb_wrapper/services/__init__.py
bb_wrapper/services/b64.py
bb_wrapper/services/barcode.py
bb_wrapper/services/barcode_cobranca.py
bb_wrapper/services/barcode_tributo.py
bb_wrapper/services/brcode.py
bb_wrapper/services/dac.py
bb_wrapper/services/document.py
bb_wrapper/services/mod.py
bb_wrapper/services/pix.py
bb_wrapper/services/pixcode.py
bb_wrapper/services/qrcode.py
bb_wrapper/services/unicode.py
bb_wrapper/utils.py
bb_wrapper/wrapper/__init__.py
bb_wrapper/wrapper/bb.py
bb_wrapper/wrapper/cobrancas.py
bb_wrapper/wrapper/pagamento_lote.py
bb_wrapper/wrapper/pix_cob.py
bb_wrapper/wrapper/request.py
bb_wrapper-0.5.5.dist-info/LICENSE.md
bb_wrapper-0.5.5.dist-info/METADATA
bb_wrapper-0.5.5.dist-info/WHEEL
bb_wrapper-0.5.5.dist-info/entry_points.txt
bb_wrapper-0.5.5.dist-info/RECORD
