Metadata-Version: 2.1
Name: bb-wrapper
Version: 0.5.5
Summary: Cliente não oficial da API do Banco do Brasil
Home-page: https://github.com/imobanco/bb-wrapper
License: GPLv3
Keywords: API,Banco,Brasil,BB,client,wrapper
Author: Imobanco
Requires-Python: >=3.9,<3.12
Classifier: Development Status :: 3 - Alpha
Classifier: Environment :: Web Environment
Classifier: Intended Audience :: Developers
Classifier: License :: OSI Approved :: GNU General Public License v3 (GPLv3)
Classifier: License :: Other/Proprietary License
Classifier: Natural Language :: Portuguese (Brazilian)
Classifier: Operating System :: OS Independent
Classifier: Programming Language :: Python :: 3
Classifier: Programming Language :: Python :: 3.9
Classifier: Programming Language :: Python :: 3.10
Classifier: Programming Language :: Python :: 3.11
Classifier: Topic :: Documentation :: Sphinx
Classifier: Topic :: Internet :: WWW/HTTP :: Dynamic Content :: CGI Tools/Libraries
Classifier: Topic :: Software Development :: Libraries :: Python Modules
Classifier: Topic :: Utilities
Requires-Dist: Unidecode (>=1.2.0,<2.0.0)
Requires-Dist: crc (>=7.1.0,<8.0.0)
Requires-Dist: pillow (==11.0.0)
Requires-Dist: pycpfcnpj (>=1.5.1,<2.0.0)
Requires-Dist: pydantic (>=2.0.0)
Requires-Dist: python-barcode (>=0.15.1,<0.16.0)
Requires-Dist: python-decouple (>=3.4,<4.0)
Requires-Dist: qrcode (>=8.0,<9.0)
Requires-Dist: requests (>=2.32.3,<3.0.0)
Project-URL: Repository, https://github.com/imobanco/bb-wrapper
